autofic_core/__init__.py
autofic_core/app.py
autofic_core/cli.py
autofic_core/errors.py
autofic_core/pipeline.py
autofic_core/ci_cd_auto/__init__.py
autofic_core/ci_cd_auto/ci_automation.py
autofic_core/download/__init__.py
autofic_core/download/github_repo_handler.py
autofic_core/llm/__init__.py
autofic_core/llm/llm_runner.py
autofic_core/llm/prompt_generator.py
autofic_core/llm/response_parser.py
autofic_core/llm/retry_prompt_generator.py
autofic_core/log/check_approval.py
autofic_core/log/log_generator.py
autofic_core/log/log_writer.py
autofic_core/patch/__init__.py
autofic_core/patch/apply_patch.py
autofic_core/patch/diff_generator.py
autofic_core/pr_auto/__init__.py
autofic_core/pr_auto/create_yml.py
autofic_core/pr_auto/env_encrypt.py
autofic_core/pr_auto/pr_procedure.py
autofic_core/sast/__init__.py
autofic_core/sast/merger.py
autofic_core/sast/snippet.py
autofic_core/sast/codeql/preprocessor.py
autofic_core/sast/codeql/runner.py
autofic_core/sast/semgrep/preprocessor.py
autofic_core/sast/semgrep/runner.py
autofic_core/sast/snykcode/preprocessor.py
autofic_core/sast/snykcode/runner.py
autofic_core/utils/__init__.py
autofic_core/utils/progress_utils.py
autofic_core/utils/ui_utils.py
autofic_core-0.1.1.dist-info/licenses/LICENSE
autofic_core-0.1.1.dist-info/METADATA
autofic_core-0.1.1.dist-info/WHEEL
autofic_core-0.1.1.dist-info/entry_points.txt
autofic_core-0.1.1.dist-info/top_level.txt
autofic_core-0.1.1.dist-info/RECORD
