Metadata-Version: 2.4
Name: autofic-core
Version: 0.1.1
Summary: A solution for remediating vulnerable source code using LLMs.
Author-email: autofic <autofic.whs@gmail.com>
License:                                  Apache License
Keywords: llm,security,autofix,static analysis,code remediation
Classifier: Programming Language :: Python :: 3
Classifier: Programming Language :: Python :: 3.8
Classifier: Programming Language :: Python :: 3.9
Classifier: Programming Language :: Python :: 3.10
Classifier: Programming Language :: Python :: 3.11
Classifier: Programming Language :: Python :: 3.12
Classifier: License :: OSI Approved :: Apache Software License
Classifier: Operating System :: OS Independent
Classifier: Development Status :: 3 - Alpha
Classifier: Intended Audience :: Developers
Classifier: Topic :: Software Development :: Build Tools
Requires-Python: >=3.8
License-File: LICENSE
Requires-Dist: certifi<2026.0.0,>=2025.4.26
Requires-Dist: cffi<2.0.0,>=1.17.1
Requires-Dist: charset-normalizer<4.0.0,>=3.4.2
Requires-Dist: click<9.0.0,>=8.1.8
Requires-Dist: cryptography<46.0.0,>=45.0.2
Requires-Dist: Deprecated<2.0.0,>=1.2.18
Requires-Dist: idna<4.0.0,>=3.10
Requires-Dist: iniconfig<3.0.0,>=2.1.0
Requires-Dist: markdown-it-py<4.0.0,>=3.0.0
Requires-Dist: mdurl<0.2.0,>=0.1.2
Requires-Dist: packaging<26.0,>=25.0
Requires-Dist: pluggy<2.0.0,>=1.6.0
Requires-Dist: pycparser<3.0.0,>=2.22
Requires-Dist: PyGithub<3.0.0,>=2.6.1
Requires-Dist: Pygments<3.0.0,>=2.19.1
Requires-Dist: PyJWT<3.0.0,>=2.10.1
Requires-Dist: PyNaCl<2.0.0,>=1.5.0
Requires-Dist: pytest<9.0.0,>=8.3.5
Requires-Dist: python-dotenv<2.0.0,>=1.1.0
Requires-Dist: requests<3.0.0,>=2.32.3
Requires-Dist: rich<14.0.0,>=13.5.2
Requires-Dist: typing_extensions<5.0.0,>=4.13.2
Requires-Dist: urllib3<3.0.0,>=2.4.0
Requires-Dist: wrapt<2.0.0,>=1.17.2
Requires-Dist: semgrep<2.0.0,>=1.122.0
Requires-Dist: pydantic<3.0.0,>=2.11.6
Requires-Dist: pydantic_core<3.0.0,>=2.33.2
Requires-Dist: openai<2.0.0,>=1.88.0
Requires-Dist: flask<4.0.0,>=3.0.3
Requires-Dist: flask-cors<7.0.0,>=6.0.1
Requires-Dist: pyfiglet<2.0.0,>=1.0.3
Dynamic: license-file
